randomized_svd/__init__.py
randomized_svd/core.py
randomized_svd/pca.py
randomized_svd/py.typed
randomized_svd/sklearn.py
randomized_svd/threshold.py
randomized_svd-0.5.0.dist-info/METADATA
randomized_svd-0.5.0.dist-info/WHEEL
randomized_svd-0.5.0.dist-info/top_level.txt
randomized_svd-0.5.0.dist-info/RECORD
