Metadata-Version: 2.4
Name: randomized-svd
Version: 0.5.0
Summary: A fast Python library for Randomized Singular Value Decomposition (rSVD).
Author-email: Massimo Fedrigo <massimo@massimofedrigo.com>
Project-URL: Homepage, https://github.com/massimofedrigo/randomized-svd
Project-URL: Bug Tracker, https://github.com/massimofedrigo/randomized-svd/issues
Keywords: linear-algebra,svd,randomized-algorithms,numpy,data-science
Classifier: Development Status :: 4 - Beta
Classifier: Intended Audience :: Science/Research
Classifier: Intended Audience :: Developers
Classifier: License :: OSI Approved :: MIT License
Classifier: Programming Language :: Python :: 3
Classifier: Topic :: Scientific/Engineering :: Mathematics
Requires-Python: >=3.9
Requires-Dist: numpy>=1.20.0
Requires-Dist: scipy>=1.7.0
Requires-Dist: scikit-learn>=1.0.0
Provides-Extra: dev
Requires-Dist: pytest; extra == "dev"
Requires-Dist: build; extra == "dev"
Requires-Dist: matplotlib; extra == "dev"
Requires-Dist: pooch; extra == "dev"
Requires-Dist: jupyter; extra == "dev"
Requires-Dist: mypy; extra == "dev"
